[
  {
    "benefit_id": "PROD_NH_DIRECT_CANCER_2601_TYPE2__BEN_075_01",
    "rider_id": "PROD_NH_DIRECT_CANCER_2601_TYPE2__RIDER_MAIN_041_01",
    "name": "암후유장해(80%이상)보험금",
    "amount_value": 100,
    "amount_text": "이 보장의 보험가입금액의 100%",
    "condition_summary": "보험기간 중 보장개시일 이후 암, 기타피부암 또는 갑상선암으로 진단 확정되고 그 질병으로 장해분류표상 장해지급률 80% 이상에 해당하는 장해상태가 되었을 때 최초 1회 지급.",
    "limit_count": 1,
    "related_concept": "CPT_CANCER_DIAGNOSIS",
    "product_id": "PROD_NH_DIRECT_CANCER_2601_TYPE2",
    "company": "NH농협손해보험",
    "product_name": "무배당 NH다이렉트암보험2601 2종(암치료집중형, 세만기형)"
  },
  {
    "benefit_id": "PROD_NH_DIRECT_CANCER_2601_TYPE2__BEN_080_01",
    "rider_id": "PROD_NH_DIRECT_CANCER_2601_TYPE2__RIDER_OPT_080_01",
    "name": "암주요치료비(유사암제외)",
    "amount_value": 100,
    "amount_text": "이 특별약관 보험가입금액의 100%(연간 1회한, 최대 10회 지급)",
    "condition_summary": "보험기간 중 보장개시일 이후 암으로 최초 진단 확정되고 보험금 지급 대상기간 이내에 암주요치료를 받은 경우 최초 진단확정일로부터 최대 10년간 연간 1회 지급.",
    "limit_count": 10,
    "related_concept": "CPT_CANCER_DIAGNOSIS",
    "product_id": "PROD_NH_DIRECT_CANCER_2601_TYPE2",
    "company": "NH농협손해보험",
    "product_name": "무배당 NH다이렉트암보험2601 2종(암치료집중형, 세만기형)"
  },
  {
    "benefit_id": "PROD_NH_DIRECT_CANCER_2601_TYPE2__BEN_088_01",
    "rider_id": "PROD_NH_DIRECT_CANCER_2601_TYPE2__RIDER_OPT_088_01",
    "name": "유사암주요치료비",
    "amount_value": 100,
    "amount_text": "이 특별약관 보험가입금액의 100%(연간 1회한, 최대 10회 지급)",
    "condition_summary": "보험기간 중 기타피부암, 갑상선암, 제자리암 또는 경계성종양으로 최초 진단 확정되고 보험금 지급 대상기간 이내에 암주요치료를 받은 경우 최초 진단확정일로부터 최대 10년간 연간 1회 지급.",
    "limit_count": 10,
    "related_concept": "CPT_SIMILAR_CANCER",
    "product_id": "PROD_NH_DIRECT_CANCER_2601_TYPE2",
    "company": "NH농협손해보험",
    "product_name": "무배당 NH다이렉트암보험2601 2종(암치료집중형, 세만기형)"
  },
  {
    "benefit_id": "PROD_NH_DIRECT_CANCER_2601_TYPE2__BEN_095_01",
    "rider_id": "PROD_NH_DIRECT_CANCER_2601_TYPE2__RIDER_OPT_095_01",
    "name": "암주요치료비(유사암제외)(상급종합병원Ⅲ)",
    "amount_value": 100,
    "amount_text": "이 특별약관 보험가입금액의 100%(연간 1회한, 최대 10회 지급)",
    "condition_summary": "보험기간 중 보장개시일 이후 암으로 최초 진단 확정되고 보험금 지급 대상기간 이내에 상급종합병원, 국립암센터, 지역암센터 또는 원자력병원에서 암주요치료를 받은 경우 최초 진단확정일로부터 최대 10년간 연간 1회 지급.",
    "limit_count": 10,
    "related_concept": "CPT_CANCER_DIAGNOSIS",
    "product_id": "PROD_NH_DIRECT_CANCER_2601_TYPE2",
    "company": "NH농협손해보험",
    "product_name": "무배당 NH다이렉트암보험2601 2종(암치료집중형, 세만기형)"
  },
  {
    "benefit_id": "PROD_NH_DIRECT_CANCER_2601_TYPE2__BEN_105_01",
    "rider_id": "PROD_NH_DIRECT_CANCER_2601_TYPE2__RIDER_OPT_105_01",
    "name": "유사암주요치료비(상급종합병원Ⅲ)",
    "amount_value": 100,
    "amount_text": "이 특별약관 보험가입금액의 100%(연간 1회한, 최대 10회 지급)",
    "condition_summary": "보험기간 중 기타피부암, 갑상선암, 제자리암 또는 경계성종양으로 최초 진단 확정되고 보험금 지급 대상기간 이내에 상급종합병원, 국립암센터, 지역암센터 또는 원자력병원에서 암주요치료를 받은 경우 최초 진단확정일로부터 최대 10년간 연간 1회 지급.",
    "limit_count": 10,
    "related_concept": "CPT_SIMILAR_CANCER",
    "product_id": "PROD_NH_DIRECT_CANCER_2601_TYPE2",
    "company": "NH농협손해보험",
    "product_name": "무배당 NH다이렉트암보험2601 2종(암치료집중형, 세만기형)"
  },
  {
    "benefit_id": "PROD_NH_DIRECT_CANCER_2601_TYPE2__BEN_114_01",
    "rider_id": "PROD_NH_DIRECT_CANCER_2601_TYPE2__RIDER_OPT_114_01",
    "name": "하이클래스 암주요치료비",
    "amount_value": 100,
    "amount_text": "이 특별약관 보험가입금액의 100%(연간 1회한, 최대 10회 지급)",
    "condition_summary": "보험기간 중 보장개시일 이후 암, 기타피부암 또는 갑상선암으로 최초 진단 확정되고 보험금 지급 대상기간 이내에 하이클래스 암주요치료를 받은 경우 최초 진단확정일로부터 최대 10년간 연간 1회 지급.",
    "limit_count": 10,
    "related_concept": "CPT_CANCER_DIAGNOSIS",
    "product_id": "PROD_NH_DIRECT_CANCER_2601_TYPE2",
    "company": "NH농협손해보험",
    "product_name": "무배당 NH다이렉트암보험2601 2종(암치료집중형, 세만기형)"
  },
  {
    "benefit_id": "PROD_NH_DIRECT_CANCER_2601_TYPE2__BEN_123_01",
    "rider_id": "PROD_NH_DIRECT_CANCER_2601_TYPE2__RIDER_OPT_123_01",
    "name": "하이클래스 암주요치료비(상급종합병원Ⅲ)",
    "amount_value": 100,
    "amount_text": "이 특별약관 보험가입금액의 100%(연간 1회한, 최대 10회 지급)",
    "condition_summary": "보험기간 중 보장개시일 이후 암, 기타피부암 또는 갑상선암으로 최초 진단 확정되고 보험금 지급 대상기간 이내에 상급종합병원, 국립암센터, 지역암센터 또는 원자력병원에서 하이클래스 암주요치료를 받은 경우 최초 진단확정일로부터 최대 10년간 연간 1회 지급.",
    "limit_count": 10,
    "related_concept": "CPT_CANCER_DIAGNOSIS",
    "product_id": "PROD_NH_DIRECT_CANCER_2601_TYPE2",
    "company": "NH농협손해보험",
    "product_name": "무배당 NH다이렉트암보험2601 2종(암치료집중형, 세만기형)"
  },
  {
    "benefit_id": "PROD_NH_DIRECT_CANCER_2601_TYPE2__BEN_134_01",
    "rider_id": "PROD_NH_DIRECT_CANCER_2601_TYPE2__RIDER_OPT_134_01",
    "name": "암주요치료비Ⅱ(유사암제외)",
    "amount_value": 100,
    "amount_text": "이 특별약관 보험가입금액의 100%(연간 1회한, 최대 10회 지급)",
    "condition_summary": "보험기간 중 보장개시일 이후 암으로 최초 진단 확정되고 보험금 지급 대상기간 이내에 암주요치료를 받은 경우 최초 진단확정일로부터 최대 10년간 연간 1회 지급.",
    "limit_count": 10,
    "related_concept": "CPT_CANCER_DIAGNOSIS",
    "product_id": "PROD_NH_DIRECT_CANCER_2601_TYPE2",
    "company": "NH농협손해보험",
    "product_name": "무배당 NH다이렉트암보험2601 2종(암치료집중형, 세만기형)"
  },
  {
    "benefit_id": "PROD_NH_DIRECT_CANCER_2601_TYPE2__BEN_143_01",
    "rider_id": "PROD_NH_DIRECT_CANCER_2601_TYPE2__RIDER_OPT_143_01",
    "name": "유사암주요치료비Ⅱ",
    "amount_value": 100,
    "amount_text": "이 특별약관 보험가입금액의 100%(연간 1회한, 최대 10회 지급)",
    "condition_summary": "보험기간 중 기타피부암, 갑상선암, 제자리암 또는 경계성종양으로 최초 진단 확정되고 보험금 지급 대상기간 이내에 암주요치료를 받은 경우 최초 진단확정일로부터 최대 10년간 연간 1회 지급.",
    "limit_count": 10,
    "related_concept": "CPT_SIMILAR_CANCER",
    "product_id": "PROD_NH_DIRECT_CANCER_2601_TYPE2",
    "company": "NH농협손해보험",
    "product_name": "무배당 NH다이렉트암보험2601 2종(암치료집중형, 세만기형)"
  },
  {
    "benefit_id": "PROD_NH_DIRECT_CANCER_2601_TYPE2__BEN_152_01",
    "rider_id": "PROD_NH_DIRECT_CANCER_2601_TYPE2__RIDER_OPT_152_01",
    "name": "암주요치료비Ⅱ(유사암제외)(상급종합병원Ⅲ)",
    "amount_value": 100,
    "amount_text": "이 특별약관 보험가입금액의 100%(연간 1회한, 최대 10회 지급)",
    "condition_summary": "보험기간 중 보장개시일 이후 암으로 최초 진단 확정되고 보험금 지급 대상기간 이내에 상급종합병원, 국립암센터, 지역암센터 또는 원자력병원에서 암주요치료를 받은 경우 최초 진단확정일로부터 최대 10년간 연간 1회 지급.",
    "limit_count": 10,
    "related_concept": "CPT_CANCER_DIAGNOSIS",
    "product_id": "PROD_NH_DIRECT_CANCER_2601_TYPE2",
    "company": "NH농협손해보험",
    "product_name": "무배당 NH다이렉트암보험2601 2종(암치료집중형, 세만기형)"
  },
  {
    "benefit_id": "PROD_NH_DIRECT_CANCER_2601_TYPE2__BEN_163_01",
    "rider_id": "PROD_NH_DIRECT_CANCER_2601_TYPE2__RIDER_OPT_163_01",
    "name": "유사암주요치료비Ⅱ(상급종합병원Ⅲ)",
    "amount_value": 100,
    "amount_text": "이 특별약관 보험가입금액의 100%(연간 1회한, 최대 10회 지급)",
    "condition_summary": "보험기간 중 기타피부암, 갑상선암, 제자리암 또는 경계성종양으로 최초 진단 확정되고 보험금 지급 대상기간 이내에 상급종합병원, 국립암센터, 지역암센터 또는 원자력병원에서 암주요치료를 받은 경우 최초 진단확정일로부터 최대 10년간 연간 1회 지급.",
    "limit_count": 10,
    "related_concept": "CPT_SIMILAR_CANCER",
    "product_id": "PROD_NH_DIRECT_CANCER_2601_TYPE2",
    "company": "NH농협손해보험",
    "product_name": "무배당 NH다이렉트암보험2601 2종(암치료집중형, 세만기형)"
  }
]